graphistry/ArrowFileUploader.py
graphistry/Engine.py
graphistry/Plottable.py
graphistry/PlotterBase.py
graphistry/__init__.py
graphistry/_version.py
graphistry/ai_utils.py
graphistry/arrow_uploader.py
graphistry/bolt_util.py
graphistry/client_session.py
graphistry/constants.py
graphistry/dgl_utils.py
graphistry/embed_utils.py
graphistry/exceptions.py
graphistry/feature_utils.py
graphistry/features.py
graphistry/gremlin.py
graphistry/hyper.py
graphistry/hyper_dask.py
graphistry/kepler.py
graphistry/layouts.py
graphistry/messages.py
graphistry/networks.py
graphistry/nodexlistry.py
graphistry/outliers.py
graphistry/plotter.py
graphistry/privacy.py
graphistry/py.typed
graphistry/pygraphistry.py
graphistry/text_utils.py
graphistry/tigeristry.py
graphistry/umap_utils.py
graphistry/util.py
graphistry/compute/ASTSerializable.py
graphistry/compute/ComputeMixin.py
graphistry/compute/__init__.py
graphistry/compute/ast.py
graphistry/compute/ast_temporal.py
graphistry/compute/calls.py
graphistry/compute/chain.py
graphistry/compute/chain_let.py
graphistry/compute/chain_remote.py
graphistry/compute/cluster.py
graphistry/compute/collapse.py
graphistry/compute/conditional.py
graphistry/compute/engine_coercion.py
graphistry/compute/exceptions.py
graphistry/compute/execution_context.py
graphistry/compute/filter_by_dict.py
graphistry/compute/gfql_unified.py
graphistry/compute/graph_operation.py
graphistry/compute/hop.py
graphistry/compute/python_remote.py
graphistry/compute/typing.py
graphistry/compute/validate_schema.py
graphistry/compute/gfql/__init__.py
graphistry/compute/gfql/call_executor.py
graphistry/compute/gfql/call_safelist.py
graphistry/compute/gfql/exceptions.py
graphistry/compute/gfql/identifiers.py
graphistry/compute/gfql/validate.py
graphistry/compute/gfql/policy/__init__.py
graphistry/compute/gfql/policy/exceptions.py
graphistry/compute/gfql/policy/shortcuts.py
graphistry/compute/gfql/policy/stats.py
graphistry/compute/gfql/policy/types.py
graphistry-0.50.3.dist-info/LICENSE.txt
graphistry-0.50.3.dist-info/METADATA
graphistry-0.50.3.dist-info/WHEEL
graphistry-0.50.3.dist-info/top_level.txt
graphistry-0.50.3.dist-info/RECORD
