Metadata-Version: 2.1
Name: graphistry
Version: 0.50.3
Summary: A visual graph analytics library for extracting, transforming, displaying, and sharing big graphs with end-to-end GPU acceleration
Home-page: https://github.com/graphistry/pygraphistry
Download-URL: https://pypi.python.org/pypi/graphistry/
Author: The Graphistry Team
Author-email: pygraphistry@graphistry.com
License: BSD
Project-URL: Homepage, https://www.graphistry.com
Project-URL: Repository, https://github.com/graphistry/pygraphistry
Project-URL: Documentation, https://pygraphistry.readthedocs.io/
Project-URL: Changelog, https://github.com/graphistry/pygraphistry/blob/master/CHANGELOG.md
Project-URL: Issues, https://github.com/graphistry/pygraphistry/issues
Project-URL: Funding, https://www.graphistry.com
Project-URL: Download, https://pypi.org/project/graphistry/#files
Project-URL: Slack, https://graphistry-community.slack.com
Project-URL: Twitter, https://twitter.com/graphistry
Project-URL: LinkedIn, https://www.linkedin.com/company/graphistry
Project-URL: Contributing, https://github.com/graphistry/pygraphistry/blob/master/CONTRIBUTING.md
Project-URL: License, https://github.com/graphistry/pygraphistry/blob/main/LICENSE.txt
Project-URL: Code of Conduct, https://github.com/graphistry/pygraphistry/blob/main/CODE_OF_CONDUCT.md
Project-URL: Support, https://www.graphistry.com/support
Keywords: cugraph,cudf,cuml,dask,Databricks,GFQL,GPU,Graph,graphviz,GraphX,Gremlin,igraph,Jupyter,Neo4j,Neptune,Network,NetworkX,Notebook,OpenSearch,Pandas,Plot,RAPIDS,RDF,Splunk,Spark,SQL,Tinkerpop,UMAP,Visualization,Torch,DGL,GNN
Platform: any
Classifier: Development Status :: 6 - Mature
Classifier: Environment :: Console
Classifier: Environment :: GPU :: NVIDIA CUDA
Classifier: License :: OSI Approved :: BSD License
Classifier: Operating System :: OS Independent
Classifier: Intended Audience :: Developers
Classifier: Intended Audience :: Information Technology
Classifier: Intended Audience :: Science/Research
Classifier: Programming Language :: Python :: 3
Classifier: Programming Language :: Python :: 3.8
Classifier: Programming Language :: Python :: 3.8
Classifier: Programming Language :: Python :: 3.9
Classifier: Programming Language :: Python :: 3.10
Classifier: Programming Language :: Python :: 3.11
Classifier: Programming Language :: Python :: 3.12
Classifier: Topic :: Internet :: Log Analysis
Classifier: Topic :: Database :: Front-Ends
Classifier: Topic :: Multimedia :: Graphics
Classifier: Topic :: Scientific/Engineering :: Artificial Intelligence
Classifier: Topic :: Scientific/Engineering :: Bio-Informatics
Classifier: Topic :: Scientific/Engineering :: Information Analysis
Classifier: Topic :: Scientific/Engineering :: Visualization
Classifier: Topic :: Sociology
Classifier: Topic :: Software Development :: Libraries
Classifier: Topic :: Software Development :: User Interfaces
Classifier: Topic :: Software Development :: Widget Sets
Classifier: Topic :: System :: Distributed Computing
Requires-Python: >=3.8
License-File: LICENSE.txt
Requires-Dist: numpy
Requires-Dist: palettable >=3.0
Requires-Dist: pandas
Requires-Dist: pyarrow >=0.15.0
Requires-Dist: requests
Requires-Dist: squarify
Requires-Dist: typing-extensions
Requires-Dist: packaging >=20.1
Requires-Dist: setuptools
Provides-Extra: ai
Requires-Dist: umap-learn ; extra == 'ai'
Requires-Dist: skrub ; extra == 'ai'
Requires-Dist: scikit-learn ; extra == 'ai'
Requires-Dist: scipy ; extra == 'ai'
Requires-Dist: torch ; extra == 'ai'
Requires-Dist: sentence-transformers ; extra == 'ai'
Requires-Dist: faiss-cpu ; extra == 'ai'
Requires-Dist: joblib ; extra == 'ai'
Provides-Extra: all
Requires-Dist: azure-identity ; extra == 'all'
Requires-Dist: torch ==2.0.1 ; extra == 'all'
Requires-Dist: neo4j ; extra == 'all'
Requires-Dist: ipython ; extra == 'all'
Requires-Dist: cugraph-cu12 ==24.12.* ; extra == 'all'
Requires-Dist: dgl ==2.1.0 ; extra == 'all'
Requires-Dist: skrub ; extra == 'all'
Requires-Dist: google-cloud-spanner ; extra == 'all'
Requires-Dist: faiss-cpu ; extra == 'all'
Requires-Dist: azure-kusto-data ; extra == 'all'
Requires-Dist: igraph ; extra == 'all'
Requires-Dist: umap-learn ; extra == 'all'
Requires-Dist: neotime ; extra == 'all'
Requires-Dist: pygraphviz ; extra == 'all'
Requires-Dist: scipy ; extra == 'all'
Requires-Dist: cudf-cu12 ==24.12.* ; extra == 'all'
Requires-Dist: torch ; extra == 'all'
Requires-Dist: joblib ; extra == 'all'
Requires-Dist: networkx >=2.5 ; extra == 'all'
Requires-Dist: cuml-cu12 ==24.12.* ; extra == 'all'
Requires-Dist: nx-cugraph-cu12 ==24.12.* ; extra == 'all'
Requires-Dist: gremlinpython ; extra == 'all'
Requires-Dist: sentence-transformers ; extra == 'all'
Requires-Dist: dask-cudf-cu12 ==24.12.* ; extra == 'all'
Requires-Dist: scikit-learn ; extra == 'all'
Requires-Dist: torchdata ==0.6.1 ; extra == 'all'
Requires-Dist: openpyxl ==3.1.0 ; extra == 'all'
Requires-Dist: xlrd ; extra == 'all'
Provides-Extra: bolt
Requires-Dist: neo4j ; extra == 'bolt'
Requires-Dist: neotime ; extra == 'bolt'
Provides-Extra: build
Requires-Dist: build ; extra == 'build'
Provides-Extra: dev
Requires-Dist: google-cloud-spanner ; extra == 'dev'
Requires-Dist: azure-identity ; extra == 'dev'
Requires-Dist: azure-kusto-data ; extra == 'dev'
Requires-Dist: igraph ; extra == 'dev'
Requires-Dist: openpyxl ==3.1.0 ; extra == 'dev'
Requires-Dist: networkx >=2.5 ; extra == 'dev'
Requires-Dist: neo4j ; extra == 'dev'
Requires-Dist: neotime ; extra == 'dev'
Requires-Dist: ipython ; extra == 'dev'
Requires-Dist: gremlinpython ; extra == 'dev'
Requires-Dist: xlrd ; extra == 'dev'
Requires-Dist: ipykernel ==6.29.5 ; extra == 'dev'
Requires-Dist: ipython ==8.28 ; extra == 'dev'
Requires-Dist: pygments >2.10 ; extra == 'dev'
Requires-Dist: build ; extra == 'dev'
Requires-Dist: myst-parser ==4.0.0 ; extra == 'dev'
Requires-Dist: flake8 >=5.0 ; extra == 'dev'
Requires-Dist: sphinx-book-theme ==1.1.3 ; extra == 'dev'
Requires-Dist: hypothesis ; extra == 'dev'
Requires-Dist: sphinx-copybutton ==0.5.2 ; extra == 'dev'
Requires-Dist: pandas-stubs ; extra == 'dev'
Requires-Dist: pytest ; extra == 'dev'
Requires-Dist: pytest-xdist ; extra == 'dev'
Requires-Dist: sphinx ==8.0.2 ; extra == 'dev'
Requires-Dist: Jinja2 ==3.1.4 ; extra == 'dev'
Requires-Dist: mock ; extra == 'dev'
Requires-Dist: mypy ; extra == 'dev'
Requires-Dist: types-tqdm ; extra == 'dev'
Requires-Dist: types-requests ; extra == 'dev'
Requires-Dist: nbsphinx ==0.9.5 ; extra == 'dev'
Requires-Dist: numba >=0.57.1 ; extra == 'dev'
Requires-Dist: rstcheck[sphinx] >=6.0 ; extra == 'dev'
Requires-Dist: docutils ==0.21.2 ; extra == 'dev'
Provides-Extra: dgl-cpu
Requires-Dist: torch ==2.0.1 ; extra == 'dgl-cpu'
Requires-Dist: torchdata ==0.6.1 ; extra == 'dgl-cpu'
Requires-Dist: dgl ==2.1.0 ; extra == 'dgl-cpu'
Provides-Extra: dgl-gpu
Requires-Dist: torch ==2.4.1 ; extra == 'dgl-gpu'
Requires-Dist: dgl-cu12 ==2.4.0 ; extra == 'dgl-gpu'
Provides-Extra: docs
Requires-Dist: docutils ==0.21.2 ; extra == 'docs'
Requires-Dist: ipython ==8.28 ; extra == 'docs'
Requires-Dist: ipykernel ==6.29.5 ; extra == 'docs'
Requires-Dist: Jinja2 ==3.1.4 ; extra == 'docs'
Requires-Dist: myst-parser ==4.0.0 ; extra == 'docs'
Requires-Dist: nbsphinx ==0.9.5 ; extra == 'docs'
Requires-Dist: pygments >2.10 ; extra == 'docs'
Requires-Dist: rstcheck[sphinx] >=6.0 ; extra == 'docs'
Requires-Dist: sphinx ==8.0.2 ; extra == 'docs'
Requires-Dist: sphinx-copybutton ==0.5.2 ; extra == 'docs'
Requires-Dist: sphinx-book-theme ==1.1.3 ; extra == 'docs'
Provides-Extra: gremlin
Requires-Dist: gremlinpython ; extra == 'gremlin'
Provides-Extra: igraph
Requires-Dist: igraph ; extra == 'igraph'
Provides-Extra: jupyter
Requires-Dist: ipython ; extra == 'jupyter'
Provides-Extra: kusto
Requires-Dist: azure-kusto-data ; extra == 'kusto'
Requires-Dist: azure-identity ; extra == 'kusto'
Provides-Extra: networkx
Requires-Dist: networkx >=2.5 ; extra == 'networkx'
Provides-Extra: nodexl
Requires-Dist: openpyxl ==3.1.0 ; extra == 'nodexl'
Requires-Dist: xlrd ; extra == 'nodexl'
Provides-Extra: pygraphviz
Requires-Dist: pygraphviz ; extra == 'pygraphviz'
Provides-Extra: rapids
Requires-Dist: cudf-cu12 ==24.12.* ; extra == 'rapids'
Requires-Dist: dask-cudf-cu12 ==24.12.* ; extra == 'rapids'
Requires-Dist: cuml-cu12 ==24.12.* ; extra == 'rapids'
Requires-Dist: cugraph-cu12 ==24.12.* ; extra == 'rapids'
Requires-Dist: nx-cugraph-cu12 ==24.12.* ; extra == 'rapids'
Provides-Extra: spanner
Requires-Dist: google-cloud-spanner ; extra == 'spanner'
Provides-Extra: test
Requires-Dist: flake8 >=5.0 ; extra == 'test'
Requires-Dist: hypothesis ; extra == 'test'
Requires-Dist: mock ; extra == 'test'
Requires-Dist: mypy ; extra == 'test'
Requires-Dist: pytest ; extra == 'test'
Requires-Dist: pytest-xdist ; extra == 'test'
Requires-Dist: pandas-stubs ; extra == 'test'
Requires-Dist: types-requests ; extra == 'test'
Requires-Dist: ipython ; extra == 'test'
Requires-Dist: types-tqdm ; extra == 'test'
Provides-Extra: testai
Requires-Dist: numba >=0.57.1 ; extra == 'testai'
Provides-Extra: umap-learn
Requires-Dist: umap-learn ; extra == 'umap-learn'
Requires-Dist: skrub ; extra == 'umap-learn'
Requires-Dist: scikit-learn ; extra == 'umap-learn'
Requires-Dist: scipy ; extra == 'umap-learn'
